.gitignore
CHANGES.txt
CONTRIBUTORS.txt
MANIFEST.in
README.rst
bootstrap.py
buildout.cfg
setup.py
collective/__init__.py
collective.js.foundation.egg-info/PKG-INFO
collective.js.foundation.egg-info/SOURCES.txt
collective.js.foundation.egg-info/dependency_links.txt
collective.js.foundation.egg-info/entry_points.txt
collective.js.foundation.egg-info/namespace_packages.txt
collective.js.foundation.egg-info/not-zip-safe
collective.js.foundation.egg-info/requires.txt
collective.js.foundation.egg-info/top_level.txt
collective/js/__init__.py
collective/js/foundation/__init__.py
collective/js/foundation/configure.zcml
collective/js/foundation/resources/css/foundation.min.css
collective/js/foundation/resources/css/normalize.css
collective/js/foundation/resources/js/foundation.master.js
collective/js/foundation/resources/js/foundation.min.js
docs/LICENSE.txt